{"organization":"Arrikto","name":"Arrikto Rok (Data Versioning)","homepage_url":"https://www.arrikto.com/","open_source":false,"repo_url":null,"logo":"arrikto.svg","twitter":"https://twitter.com/arrikto","crunchbase":"https://www.crunchbase.com/organization/no-data","components":null,"image_data":{"fileName":"arrikto-rok-data-versioning.svg","hash":"UwW8x3ZgwL2h/SjTm3l0oz49EKgNVmVXo3qI8bujo2k="},"firstCommitLink":null,"latestCommitLink":null,"commitsThisYear":0,"language":null,"license":"NotOpenSource","headquarters":"N/A","latestTweetDate":{"text":"about a month","value":"960","original":"2021-05-12T17:03:59.000Z"},"description":null,"crunchbaseData":{"acquisitions":[],"funding":"","description":"","homepage":"","city":"","region":"","country":"","twitter":"","linkedin":"","ticker":"","kind":"","numEmployeesMin":"","numEmployeesMax":""},"path":"Data Governance and Security / Data Versioning","landscape":"Data Governance and Security / Data Versioning","category":"Data Governance and Security","amount":"N/A","oss":false,"href":"logos/arrikto-rok-data-versioning.svg","bestPracticeBadgeId":false,"bestPracticePercentage":null,"industries":[],"id":"arrikto-rok-data-versioning","flatName":"Arrikto Rok (Data Versioning)","member":false,"relation":false,"isSubsidiaryProject":false}