{"organization":"cnvrg.io","name":"cnvrg.io (Dashboards and Charts)","homepage_url":"https://cnvrg.io/","open_source":false,"repo_url":null,"logo":"cnvrg.svg","twitter":"https://twitter.com/cnvrg_io","crunchbase":"https://www.crunchbase.com/organization/no-data","components":null,"status":["certified","ubi"],"use_cases":"ML w Jupyter Notebook, ML Model Serving","use_cases_filter":["ml_w_jupyter_notebook","ml_model_serving"],"image_data":{"fileName":"cnvrg-io-dashboards-and-charts.svg","hash":"z0pzeBwJly5V1PsPizUPFpjlTNCv9owsw4d/ukunL3c="},"firstCommitLink":null,"latestCommitLink":null,"commitsThisYear":0,"language":null,"license":"NotOpenSource","headquarters":"N/A","latestTweetDate":{"text":"about a month","value":"960","original":"2021-05-11T15:40:02.000Z"},"description":null,"crunchbaseData":{"acquisitions":[],"funding":"","description":"","homepage":"","city":"","region":"","country":"","twitter":"","linkedin":"","ticker":"","kind":"","numEmployeesMin":"","numEmployeesMax":""},"path":"Data Analysis / Dashboards and Charts","landscape":"Data Analysis / Dashboards and Charts","category":"Data Analysis","amount":"N/A","oss":false,"href":"logos/cnvrg-io-dashboards-and-charts.svg","bestPracticeBadgeId":false,"bestPracticePercentage":null,"industries":[],"id":"cnvrg-io-dashboards-and-charts","flatName":"cnvrg.io (Dashboards and Charts)","member":false,"relation":false,"isSubsidiaryProject":false}