{"organization":"IBM","name":"IBM Streams (Business Intelligence)","homepage_url":"https://www.ibm.com/cloud/streaming-analytics","open_source":false,"repo_url":null,"logo":"ibm.svg","twitter":"https://twitter.com/IBMcloud","crunchbase":"https://www.crunchbase.com/organization/no-data","components":null,"image_data":{"fileName":"ibm-streams-business-intelligence.svg","hash":"ZjpUH4pNt5l4oDV4GctJSS85QJTidUBMfrDP2Kl4y8w="},"firstCommitLink":null,"latestCommitLink":null,"commitsThisYear":0,"language":null,"license":"NotOpenSource","headquarters":"N/A","latestTweetDate":{"text":"about a month","value":"960","original":"2021-05-14T11:18:18.000Z"},"description":null,"crunchbaseData":{"acquisitions":[],"funding":"","description":"","homepage":"","city":"","region":"","country":"","twitter":"","linkedin":"","ticker":"","kind":"","numEmployeesMin":"","numEmployeesMax":""},"path":"Data Analysis / Business Intelligence","landscape":"Data Analysis / Business Intelligence","category":"Data Analysis","amount":"N/A","oss":false,"href":"logos/ibm-streams-business-intelligence.svg","bestPracticeBadgeId":false,"bestPracticePercentage":null,"industries":[],"id":"ibm-streams-business-intelligence","flatName":"IBM Streams (Business Intelligence)","member":false,"relation":false,"isSubsidiaryProject":false}