{"organization":"Preset","name":"Preset (Dashboards and Charts)","homepage_url":"https://preset.io","open_source":true,"repo_url":null,"logo":"preset.svg","crunchbase":"https://www.crunchbase.com/organization/no-data","components":null,"status":["odh"],"use_cases":"Data Acquisition and Preparation","use_cases_filter":["data_acquisition_and_preparation"],"image_data":{"fileName":"preset-dashboards-and-charts.svg","hash":"9EZF1YHhc4Ss1SfU9U13Cd6RLHw1VYqrTKANTcyE6KI="},"firstCommitLink":null,"latestCommitLink":null,"commitsThisYear":0,"language":null,"license":"Unknown License","headquarters":"N/A","description":null,"crunchbaseData":{"acquisitions":[],"funding":"","description":"","homepage":"","city":"","region":"","country":"","twitter":"","linkedin":"","ticker":"","kind":"","numEmployeesMin":"","numEmployeesMax":""},"path":"Data Analysis / Dashboards and Charts","landscape":"Data Analysis / Dashboards and Charts","category":"Data Analysis","amount":"N/A","oss":true,"href":"logos/preset-dashboards-and-charts.svg","bestPracticeBadgeId":false,"bestPracticePercentage":null,"industries":[],"id":"preset-dashboards-and-charts","flatName":"Preset (Dashboards and Charts)","member":false,"relation":false,"isSubsidiaryProject":false}