{"organization":"Tamr","name":"Tamr (Data Encryption)","homepage_url":"https://www.tamr.com/","open_source":false,"repo_url":null,"logo":"tamr.svg","crunchbase":"https://www.crunchbase.com/organization/no-data","components":null,"image_data":{"fileName":"tamr-data-encryption.svg","hash":"pUd3Ws1uxmYP8i3LNIRBl8uUh7UqIs2PKIKeosi68AA="},"firstCommitLink":null,"latestCommitLink":null,"commitsThisYear":0,"language":null,"license":"NotOpenSource","headquarters":"N/A","description":null,"crunchbaseData":{"acquisitions":[],"funding":"","description":"","homepage":"","city":"","region":"","country":"","twitter":"","linkedin":"","ticker":"","kind":"","numEmployeesMin":"","numEmployeesMax":""},"path":"Data Governance and Security / Data Encryption","landscape":"Data Governance and Security / Data Encryption","category":"Data Governance and Security","amount":"N/A","oss":false,"href":"logos/tamr-data-encryption.svg","bestPracticeBadgeId":false,"bestPracticePercentage":null,"industries":[],"id":"tamr-data-encryption","flatName":"Tamr (Data Encryption)","member":false,"relation":false,"isSubsidiaryProject":false}