{"organization":"Weka.io","name":"Weka.io WekaIO (Hardware Acceleration)","homepage_url":"https://www.weka.io/","open_source":false,"repo_url":null,"logo":"weka-io.svg","twitter":"https://twitter.com/wekaio","crunchbase":"https://www.crunchbase.com/organization/no-data","components":null,"image_data":{"fileName":"weka-io-weka-io-hardware-acceleration.svg","hash":"Lt+UbiEXxN9GG68oXzhStahBmGBQhUUOo+IjSjSkRgw="},"firstCommitLink":null,"latestCommitLink":null,"commitsThisYear":0,"language":null,"license":"NotOpenSource","headquarters":"N/A","latestTweetDate":{"text":"about a month","value":"960","original":"2021-05-13T21:08:35.000Z"},"description":null,"crunchbaseData":{"acquisitions":[],"funding":"","description":"","homepage":"","city":"","region":"","country":"","twitter":"","linkedin":"","ticker":"","kind":"","numEmployeesMin":"","numEmployeesMax":""},"path":"Infrastructure / Hardware Acceleration","landscape":"Infrastructure / Hardware Acceleration","category":"Infrastructure","amount":"N/A","oss":false,"href":"logos/weka-io-weka-io-hardware-acceleration.svg","bestPracticeBadgeId":false,"bestPracticePercentage":null,"industries":[],"id":"weka-io-weka-io-hardware-acceleration","flatName":"Weka.io WekaIO (Hardware Acceleration)","member":false,"relation":false,"isSubsidiaryProject":false}